decorator_include.py
django_decorator_include-3.0.dist-info/LICENSE
django_decorator_include-3.0.dist-info/METADATA
django_decorator_include-3.0.dist-info/WHEEL
django_decorator_include-3.0.dist-info/top_level.txt
django_decorator_include-3.0.dist-info/zip-safe
django_decorator_include-3.0.dist-info/RECORD
